LICENSE
MANIFEST.in
README.md
quicktest.py
settings_test.py
setup.py
django_vkontakte_groups_migration.egg-info/PKG-INFO
django_vkontakte_groups_migration.egg-info/SOURCES.txt
django_vkontakte_groups_migration.egg-info/dependency_links.txt
django_vkontakte_groups_migration.egg-info/not-zip-safe
django_vkontakte_groups_migration.egg-info/requires.txt
django_vkontakte_groups_migration.egg-info/top_level.txt
vkontakte_groups_migration/__init__.py
vkontakte_groups_migration/__init__.pyc
vkontakte_groups_migration/admin.py
vkontakte_groups_migration/admin.pyc
vkontakte_groups_migration/factories.py
vkontakte_groups_migration/factories.pyc
vkontakte_groups_migration/models.py
vkontakte_groups_migration/models.pyc
vkontakte_groups_migration/signals.py
vkontakte_groups_migration/signals.pyc
vkontakte_groups_migration/tasks.py
vkontakte_groups_migration/tasks.pyc
vkontakte_groups_migration/tests.py
vkontakte_groups_migration/tests.pyc
vkontakte_groups_migration/migrations/0001_initial.py
vkontakte_groups_migration/migrations/0001_initial.pyc
vkontakte_groups_migration/migrations/0002_auto__add_field_groupmigration_hidden.py
vkontakte_groups_migration/migrations/0002_auto__add_field_groupmigration_hidden.pyc
vkontakte_groups_migration/migrations/0003_auto__del_field_groupmigration_members_deactivated_entered__del_field_.py
vkontakte_groups_migration/migrations/0003_auto__del_field_groupmigration_members_deactivated_entered__del_field_.pyc
vkontakte_groups_migration/migrations/0004_auto.py
vkontakte_groups_migration/migrations/0004_auto.pyc
vkontakte_groups_migration/migrations/0005_auto__add_groupmembership__add_unique_groupmembership_group_user_id_ti.py
vkontakte_groups_migration/migrations/0005_auto__add_groupmembership__add_unique_groupmembership_group_user_id_ti.pyc
vkontakte_groups_migration/migrations/0005_auto__add_groupmigrationuser__add_groupmigrationnew__add_unique_groupm.pyc
vkontakte_groups_migration/migrations/0006_auto__chg_field_groupmigrationuser_migration__add_unique_groupmigratio.pyc
vkontakte_groups_migration/migrations/0006_auto__del_unique_groupmembership_user_id_time_entered_group__del_uniqu.py
vkontakte_groups_migration/migrations/0006_auto__del_unique_groupmembership_user_id_time_entered_group__del_uniqu.pyc
