Metadata-Version: 1.1
Name: django-vkontakte-groups-migration
Version: 0.6.0
Summary: Django implementation for vkontakte API Groups Users Migration
Home-page: https://github.com/ramusus/django-vkontakte-groups-migration
Author: ramusus
Author-email: ramusus@gmail.com
License: BSD
Download-URL: http://pypi.python.org/pypi/django-vkontakte-groups-migration
Platform: UNKNOWN
Classifier: Development Status :: 4 - Beta
Classifier: Environment :: Web Environment
Classifier: Intended Audience :: Developers
Classifier: License :: OSI Approved :: BSD License
Classifier: Operating System :: OS Independent
Classifier: Programming Language :: Python
Classifier: Topic :: Software Development :: Libraries :: Python Modules
